mytry/__init__.py
mytry1234-0.1.dist-info/DESCRIPTION.rst
mytry1234-0.1.dist-info/METADATA
mytry1234-0.1.dist-info/RECORD
mytry1234-0.1.dist-info/WHEEL
mytry1234-0.1.dist-info/metadata.json
mytry1234-0.1.dist-info/top_level.txt
