Metadata-Version: 2.0
Name: mytry1234
Version: 0.1
Summary: First try for package
Home-page: https://github.com/akash0824/mytry
Author: akash0824
Author-email: akashkumar0824@gmail.com
License: UNKNOWN
Platform: UNKNOWN
